uiinspector/__init__.py
uiinspector/icons.py
uiinspector/icons.qrc
uiinspector/style.qss
uiinspector/uiinspector.py
uiinspector/common/__init__.py
uiinspector/common/exceptions.py
uiinspector/common/utils.py
uiinspector/core/__init__.py
uiinspector/core/pyjab.py
uiinspector/core/selenium.py
uiinspector/core/base/__init__.py
uiinspector/core/tree/__init__.py
uiinspector/core/tree/jabtree.py
uiinspector/core/tree/uiatree.py
uiinspector/win32/__init__.py
uiinspector/win32/functions.py
uiinspector/win32/structures.py
uiinspector-1.0.3.dist-info/LICENSE
uiinspector-1.0.3.dist-info/METADATA
uiinspector-1.0.3.dist-info/WHEEL
uiinspector-1.0.3.dist-info/entry_points.txt
uiinspector-1.0.3.dist-info/top_level.txt
uiinspector-1.0.3.dist-info/RECORD
